pythonesque/__init__.py
pythonesque/series.py
pythonesque-0.0.3.dist-info/LICENSE
pythonesque-0.0.3.dist-info/WHEEL
pythonesque-0.0.3.dist-info/METADATA
pythonesque-0.0.3.dist-info/RECORD
