Metadata-Version: 2.1
Name: pythonesque
Version: 0.0.3
Summary: Pythonesque is a package of functions to make Python code more readable to non-Python programmers.
Author-email: ryno8 <ryan.jk.ong1@gmail.com>
Classifier: License :: OSI Approved :: MIT License
Project-URL: Home, https://ryno8.github.io/pythonesque/
